hana_automl/__init__.py
hana_automl/automl.py
hana_automl/storage.py
hana_automl/algorithms/__init__.py
hana_automl/algorithms/base_algo.py
hana_automl/algorithms/classification/__init__.py
hana_automl/algorithms/classification/decisiontreecls.py
hana_automl/algorithms/classification/gradboostcls.py
hana_automl/algorithms/classification/hybgradboostcls.py
hana_automl/algorithms/classification/kneighborscls.py
hana_automl/algorithms/classification/logregressioncls.py
hana_automl/algorithms/classification/mlpcl.py
hana_automl/algorithms/classification/naive_bayes.py
hana_automl/algorithms/classification/rdtclas.py
hana_automl/algorithms/classification/svc.py
hana_automl/algorithms/ensembles/__init__.py
hana_automl/algorithms/ensembles/blendcls.py
hana_automl/algorithms/ensembles/blending.py
hana_automl/algorithms/ensembles/blendreg.py
hana_automl/algorithms/regression/__init__.py
hana_automl/algorithms/regression/decisiontreereg.py
hana_automl/algorithms/regression/expreg.py
hana_automl/algorithms/regression/glmreg.py
hana_automl/algorithms/regression/gradboostreg.py
hana_automl/algorithms/regression/hybgradboostreg.py
hana_automl/algorithms/regression/kneighborsreg.py
hana_automl/algorithms/regression/mlpreg.py
hana_automl/algorithms/regression/rdtreg.py
hana_automl/algorithms/regression/svr.py
hana_automl/metric/__init__.py
hana_automl/metric/mae.py
hana_automl/metric/mse.py
hana_automl/metric/rmse.py
hana_automl/optimizers/__init__.py
hana_automl/optimizers/base_optimizer.py
hana_automl/optimizers/bayes.py
hana_automl/optimizers/optuna_optimizer.py
hana_automl/pipeline/__init__.py
hana_automl/pipeline/data.py
hana_automl/pipeline/input.py
hana_automl/pipeline/modelres.py
hana_automl/pipeline/pipeline.py
hana_automl/preprocess/__init__.py
hana_automl/preprocess/preprocessor.py
hana_automl/preprocess/settings.py
hana_automl/utils/__init__.py
hana_automl/utils/error.py
hana_automl/utils/logger.py
hana_automl/utils/scripts.py
hana_automl-0.0.5.dist-info/LICENSE
hana_automl-0.0.5.dist-info/WHEEL
hana_automl-0.0.5.dist-info/METADATA
hana_automl-0.0.5.dist-info/RECORD
