Metadata-Version: 2.1
Name: hana_automl
Version: 0.0.5
Summary: Welcome to hana_automl - Automated Machine Learning library based on SAP HANA.
Home-page: https://github.com/dan0nchik/SAP-HANA-AutoML
Author: Daniel Khromov, Egor Pavlov
Author-email: dan0nchik@ya.ru, pavlov.erg@gmail.com
Requires-Python: >=3.6
Classifier: License :: OSI Approved :: MIT License
Classifier: Intended Audience :: Developers
Classifier: Programming Language :: Python :: 3
Requires-Dist: cryptography
Requires-Dist: Cython
Requires-Dist: numpy
Requires-Dist: bayesian_optimization
Requires-Dist: scipy
Requires-Dist: requests
Requires-Dist: pandas
Requires-Dist: optuna
Requires-Dist: hana-ml
Requires-Dist: omegaconf
Requires-Dist: scikit-learn ==0.22
